{
  "Mitsugan Miyamoto": [
    {
      "name": "Reprisal",
      "time": 10
    },
    {
      "name": "Heart of Light",
      "time": 30
    },
    {
      "name": "Heart of Light",
      "time": 90
    },
    {
      "name": "Reprisal",
      "time": 120
    }
  ],
  "Aerry Berry": [
    {
      "name": "Reprisal",
      "time": 10
    },
    {
      "name": "Shake It Off",
      "time": 60
    },
    {
      "name": "Reprisal",
      "time": 120
    }
  ],
  "Cup Noodles": [
    {
      "name": "Reprisal",
      "time": 10
    }
  ],
  "Kiwi Fruitiwi": [
    {
      "name": "Heart of Light",
      "time": 30
    },
    {
      "name": "Heart of Light",
      "time": 90
    }
  ],
  "Moomba Shumi": [
    {
      "name": "Curing Waltz",
      "time": 10
    },
    {
      "name": "Shield Samba",
      "time": 30
    }
  ],
  "Winry Fruitiwi": [
    {
      "name": "Star Prism",
      "time": 10
    },
    {
      "name": "Tempera Grassa",
      "time": 15
    }
  ],
  "Cody Berry": [
    {
      "name": "Addle",
      "time": 10
    },
    {
      "name": "Magick Barrier",
      "time": 30
    }
  ],
  "Player Hana": [
    {
      "name": "Feint",
      "time": 10
    },
    {
      "name": "Feint",
      "time": 120
    }
  ]
}